aladdin_connect/__init__.py
aladdin_connect/session_manager.py
aladdin_connect-0.4.dist-info/LICENSE
aladdin_connect-0.4.dist-info/METADATA
aladdin_connect-0.4.dist-info/WHEEL
aladdin_connect-0.4.dist-info/top_level.txt
aladdin_connect-0.4.dist-info/RECORD
