Metadata-Version: 2.1
Name: aladdin-connect
Version: 0.4
Summary: Python API for controlling Genie garage doors connected to Aladdin Connect devices
Home-page: http://github.com/shoejosh/aladdin-connect
Author: Josh Shoemaker
Author-email: shoejosh@gmail.com
License: MIT
Platform: UNKNOWN
Classifier: Development Status :: 4 - Beta
Classifier: Intended Audience :: Developers
Classifier: License :: OSI Approved :: MIT License
Classifier: Operating System :: OS Independent
Classifier: Programming Language :: Python
License-File: LICENSE
Requires-Dist: requests
